py_rejseplan/__init__.py
py_rejseplan/__main__.py
py_rejseplan/constants.py
py_rejseplan/enums.py
py_rejseplan/api/base.py
py_rejseplan/api/departures.py
py_rejseplan/dataclasses/constants.py
py_rejseplan/dataclasses/departure.py
py_rejseplan/dataclasses/departure_board.py
py_rejseplan/dataclasses/enums.py
py_rejseplan/dataclasses/journey_detail_ref.py
py_rejseplan/dataclasses/mixins.py
py_rejseplan/dataclasses/note.py
py_rejseplan/dataclasses/product_type.py
py_rejseplan/dataclasses/stop.py
py_rejseplan/dataclasses/technical_message.py
py_rejseplan/dataclasses/technical_messages.py
py_rejseplan/dataclasses/transport_mappings.py
py_rejseplan/exceptions/__init__.py
py_rejseplan/exceptions/api_error.py
py_rejseplan/exceptions/base_error.py
py_rejseplan/exceptions/connection_error.py
py_rejseplan/exceptions/departure_api_error.py
py_rejseplan/exceptions/departure_error.py
py_rejseplan/exceptions/http_error.py
py_rejseplan/exceptions/validation_error.py
py_rejseplan/version/__init__.py
py_rejseplan/version/__version__.py
pyrejseplan-1.0.6.dist-info/licenses/LICENSE
pyrejseplan-1.0.6.dist-info/METADATA
pyrejseplan-1.0.6.dist-info/WHEEL
pyrejseplan-1.0.6.dist-info/entry_points.txt
pyrejseplan-1.0.6.dist-info/top_level.txt
pyrejseplan-1.0.6.dist-info/RECORD
