Metadata-Version: 2.4
Name: pyRejseplan
Version: 1.0.6
Summary: Python interface with rejseplanens API 2.0 based on HAFAS
Author-email: Jacob Warrer <Jacobwarrer@gmail.com>
Maintainer-email: Jacob Warrer <Jacobwarrer@gmail.com>
License-Expression: MIT
Project-URL: Homepage, https://github.com/Jawar19/pyRejseplan
Project-URL: Issues, https://github.com/Jawar19/pyRejseplan/issues
Project-URL: Repository, https://github.com/Jawar19/pyRejseplan
Classifier: Development Status :: 3 - Alpha
Classifier: Programming Language :: Python :: 3
Classifier: Operating System :: OS Independent
Requires-Python: <3.14,>=3.8
License-File: LICENSE
Requires-Dist: requests>=2.32.2
Requires-Dist: urllib3>=1.26.5
Requires-Dist: pydantic-xml>=2.17.0
Dynamic: license-file
